sholl/__init__.py
sholl/__main__.py
sholl/lint.py
sholl/sholl.py
sholl/templates.py
sholl/util.py
sholl/version.py
sholl-0.0.6.dist-info/entry_points.txt
sholl-0.0.6.dist-info/LICENSE
sholl-0.0.6.dist-info/WHEEL
sholl-0.0.6.dist-info/METADATA
sholl-0.0.6.dist-info/RECORD
